AUTHORS.rst
CONTRIBUTING.rst
HISTORY.rst
LICENSE
MANIFEST.in
README.rst
setup.py
boilerplate/__init__.py
boilerplate/boilerplate.py
boilerplate/mail.py
boilerplate/mixins.py
boilerplate/models.py
boilerplate/signals.py
boilerplate/tests.py
boilerplate/utils.py
boilerplate/templatetags/__init__.py
boilerplate/templatetags/boilerplate.py
demo/manage.py
demo/account/__init__.py
demo/account/admin.py
demo/account/apps.py
demo/account/models.py
demo/account/tests.py
demo/account/urls.py
demo/account/views.py
demo/account/migrations/__init__.py
demo/account/templates/account/login.html
demo/account/templates/account/password.html
demo/account/templates/account/recover.html
demo/account/templates/account/registration.html
demo/demo/__init__.py
demo/demo/settings.py
demo/demo/urls.py
demo/demo/wsgi.py
demo/store/__init__.py
demo/store/admin.py
demo/store/apps.py
demo/store/forms.py
demo/store/models.py
demo/store/test.py
demo/store/urls.py
demo/store/views.py
demo/store/migrations/0001_initial.py
demo/store/migrations/__init__.py
demo/store/templates/store/actor_form.html
demo/store/templates/store/actor_list.html
demo/store/templates/store/movie_form.html
demo/store/templates/store/movie_list.html
demo/templates/base.html
demo/templates/form-title.html
demo/templates/form.html
demo/templates/formset.html
demo/templates/menu.html
demo/templates/mail/recover-account.html
django_boilerplate.egg-info/PKG-INFO
django_boilerplate.egg-info/SOURCES.txt
django_boilerplate.egg-info/dependency_links.txt
django_boilerplate.egg-info/not-zip-safe
django_boilerplate.egg-info/requires.txt
django_boilerplate.egg-info/top_level.txt